MANIFEST.in
README.rst
README.txt
setup.py
buildouts/plone4/buildout.cfg
buildouts/plone4/install.sh
buildouts/plone4/versions.cfg
collective/__init__.py
collective.diffbot.egg-info/PKG-INFO
collective.diffbot.egg-info/SOURCES.txt
collective.diffbot.egg-info/dependency_links.txt
collective.diffbot.egg-info/entry_points.txt
collective.diffbot.egg-info/namespace_packages.txt
collective.diffbot.egg-info/not-zip-safe
collective.diffbot.egg-info/requires.txt
collective.diffbot.egg-info/top_level.txt
collective/diffbot/README.rst
collective/diffbot/README.txt
collective/diffbot/__init__.py
collective/diffbot/configure.zcml
collective/diffbot/interfaces.py
collective/diffbot/profiles.zcml
collective/diffbot/version.txt
collective/diffbot/browser/__init__.py
collective/diffbot/browser/configure.zcml
collective/diffbot/browser/app/__init__.py
collective/diffbot/browser/app/controlpanel.py
collective/diffbot/browser/app/view.py
collective/diffbot/browser/img/icon.gif
collective/diffbot/browser/img/loader.gif
collective/diffbot/browser/js/view.js
collective/diffbot/cache/__init__.py
collective/diffbot/cache/cache.py
collective/diffbot/cache/configure.zcml
collective/diffbot/cache/nocache.py
collective/diffbot/locales/collective.pot
collective/diffbot/locales/update.sh
collective/diffbot/locales/en/LC_MESSAGES/collective.po
collective/diffbot/locales/ro/LC_MESSAGES/collective.po
collective/diffbot/profiles/default/controlpanel.xml
collective/diffbot/profiles/default/jsregistry.xml
collective/diffbot/profiles/default/metadata.xml
collective/diffbot/profiles/default/registry.xml
collective/diffbot/profiles/uninstall/jsregistry.xml
collective/diffbot/upgrades/__init__.py
collective/diffbot/upgrades/configure.zcml
docs/HISTORY.txt