Metadata-Version: 1.1
Name: collective.diffbot
Version: 1.0
Summary: difbot.com wrapper for Plone usage
Home-page: http://plone/org/products/collective.diffbot
Author: Alin Voinea
Author-email: contact@avoinea.com
License: GPL
Keywords: collective diffbot plone zope
Platform: UNKNOWN
Classifier: Framework :: Zope2
Classifier: Framework :: Zope3
Classifier: Framework :: Plone
Classifier: Framework :: Plone :: 4.0
Classifier: Framework :: Plone :: 4.1
Classifier: Framework :: Plone :: 4.2
Classifier: Programming Language :: Zope
Classifier: Programming Language :: Python
Classifier: Topic :: Software Development :: Libraries :: Python Modules
Classifier: License :: OSI Approved :: GNU General Public License (GPL)
